{
 "pageTitle": "Reducing road danger",
 "keywords": "Coach drivers,Drivers,Freight industry,Taxi and private hire,Safety and security,Cycling,Driving,Motorcycle,Walking,TfL",
 "description": "Schemes and activities to help achieve safer roads for all in London",
 "template": "page-cards",
 "breadcrumbs": [
  {
   "style": "home",
   "title": "Home",
   "url": "/"
  },
  {
   "title": "Safety \u0026 security",
   "url": "/corporate/safety-and-security/index"
  },
  {
   "title": "Reducing road danger"
  }
 ],
 "title": {
  "title": "Reducing road danger",
  "card": {
   "link": {
    "image": {}
   },
   "image": {},
   "wrapped": false
  }
 },
 "body": {
  "primarys": [
   {
    "style": "card-top ",
    "title": "Vision Zero for London",
    "texts": [
     "Together we can eradicate deaths and serious injuries from London's transport network"
    ],
    "link": {
     "url": "/corporate/safety-and-security/road-safety/vision-zero-for-london",
     "image": {}
    },
    "image": {
     "url": "https://tfl.gov.uk/cdn/static/cms/images/promos/vision-zero-700.jpg"
    },
    "wrapped": false
   }
  ],
  "cards": [
   {
    "title": "Safe speeds",
    "texts": [
     "Speed is a factor in at least 37% of serious collisions in London"
    ],
    "link": {
     "url": "/corporate/safety-and-security/road-safety/safe-speeds",
     "image": {}
    },
    "image": {
     "url": "https://tfl.gov.uk/cdn/static/cms/images/promos/safe-speed-20mph_rdax_400x200.jpg"
    },
    "wrapped": false
   },
   {
    "title": "Direct Vision Standard",
    "texts": [
     "Making London's lorries safer with a new Safety Permit for HGVs"
    ],
    "link": {
     "url": "/info-for/deliveries-in-london/delivering-safely/direct-vision-in-heavy-goods-vehicles",
     "image": {}
    },
    "image": {
     "url": "https://tfl.gov.uk/cdn/static/cms/images/promos/lorry-junction-700_rdax_400x200.jpg"
    },
    "wrapped": false
   },
   {
    "title": "Improving London's roads",
    "texts": [
     "We're building 73 Safer Junctions around London, with 29 already complete"
    ],
    "link": {
     "url": "/campaign/our-plan-for-londons-roads",
     "image": {}
    },
    "image": {
     "url": "https://tfl.gov.uk/cdn/static/cms/images/promos/old-street-safer_rdax_400x200.jpg"
    },
    "wrapped": false
   },
   {
    "title": "Bus safety",
    "texts": [
     "See how we are continuously driving major safety improvements on our buses"
    ],
    "link": {
     "url": "/corporate/safety-and-security/road-safety/bus-safety",
     "image": {}
    },
    "image": {
     "url": "https://tfl.gov.uk/cdn/static/cms/images/promos/bus-safety_rdax_400x200.jpg"
    },
    "wrapped": false
   },
   {
    "title": "London collision map",
    "texts": [
     "Learn where road traffic collisions have happened in London since 2005"
    ],
    "link": {
     "url": "/corporate/safety-and-security/road-safety/london-collision-map",
     "image": {}
    },
    "image": {
     "url": "https://tfl.gov.uk/cdn/static/cms/images/promos/collisionmaplondon_rdax_400x200.gif"
    },
    "wrapped": false
   }
  ]
 },
 "rhnav": {
  "cards": [
   {
    "template": "listgroup",
    "style": "foldernav",
    "title": "Reducing road danger",
    "links": [
     {
      "title": "Vision Zero for London",
      "url": "/corporate/safety-and-security/road-safety/vision-zero-for-london",
      "image": {}
     },
     {
      "title": "London collision map",
      "url": "/corporate/safety-and-security/road-safety/london-collision-map",
      "image": {}
     },
     {
      "title": "Safety cameras",
      "url": "/corporate/safety-and-security/road-safety/safety-enforcement-cameras",
      "image": {}
     },
     {
      "title": "Bus safety",
      "url": "/corporate/safety-and-security/road-safety/bus-safety",
      "image": {}
     },
     {
      "title": "Cycle safety",
      "url": "/corporate/safety-and-security/road-safety/cycle-safety",
      "image": {}
     },
     {
      "title": "Driver safety",
      "url": "/corporate/safety-and-security/road-safety/driver-safety",
      "image": {}
     },
     {
      "title": "Community Roadwatch",
      "url": "/corporate/safety-and-security/road-safety/community-roadwatch",
      "image": {}
     }
    ],
    "link": {
     "title": "Reducing road danger",
     "url": "/corporate/safety-and-security/road-safety/community-roadwatch",
     "image": {}
    },
    "image": {},
    "wrapped": false
   },
   {
    "template": "advert",
    "link": {
     "image": {}
    },
    "image": {},
    "wrapped": false
   }
  ]
 }
}