{
 "pageTitle": "Improvements \u0026 projects",
 "keywords": "TfL",
 "description": "We run dozens of projects at any one time all over the Capital to improve the journeys of London's residents and visitors - these are a few of the most high-profile projects",
 "template": "page-cards",
 "breadcrumbs": [
  {
   "style": "home",
   "title": "Home",
   "url": "/"
  },
  {
   "title": "Improvements \u0026 projects"
  }
 ],
 "title": {
  "complex": true,
  "title": "Improvements \u0026 projects",
  "background": "https://tfl.gov.uk/cdn/static/cms/images/promos/good-news-section.jpg",
  "card": {
   "link": {
    "image": {}
   },
   "image": {},
   "wrapped": false
  }
 },
 "body": {
  "primarys": [
   {
    "texts": [
     "We are committed to continually improving your services, whether it's the Tube, buses, London Overground, DLR, TfL Rail, trams, roads or Cycleways. Find out more about specific projects we're working on below."
    ],
    "link": {
     "image": {}
    },
    "image": {},
    "wrapped": false
   }
  ],
  "cards": [
   {
    "title": "Improving the Tube",
    "texts": [
     "Find out what we're doing to upgrade trains, stations and services"
    ],
    "link": {
     "url": "/campaign/tube-improvements",
     "image": {}
    },
    "image": {
     "url": "https://tfl.gov.uk/cdn/static/cms/images/promos/revealing-underground-livery_rdax_400x200.jpg"
    },
    "wrapped": false
   },
   {
    "title": "Improving buses",
    "texts": [
     "New technology is helping us operate cleaner buses and improve services"
    ],
    "link": {
     "url": "/modes/buses/improving-buses",
     "image": {}
    },
    "image": {
     "url": "https://tfl.gov.uk/cdn/static/cms/images/promos/ip-green-bus-teaser_rdax_400x200.jpg"
    },
    "wrapped": false
   },
   {
    "title": "Improving the DLR",
    "texts": [
     "New trains will bring more frequent and reliable journeys from 2023"
    ],
    "link": {
     "url": "/modes/dlr/improving-the-dlr",
     "image": {}
    },
    "image": {
     "url": "https://tfl.gov.uk/cdn/static/cms/images/promos/dlr-train-water-teaser_rdax_400x200.jpg"
    },
    "wrapped": false
   },
   {
    "title": "Improving London Overground",
    "texts": [
     "You'll find trains will be running more frequently on parts of the line"
    ],
    "link": {
     "url": "/modes/london-overground/improving-london-overground",
     "image": {}
    },
    "image": {
     "url": "https://tfl.gov.uk/cdn/static/cms/images/promos/lo-new-train-teaser_rdax_400x200.jpg"
    },
    "wrapped": false
   },
   {
    "title": "Improving TfL Rail",
    "texts": [
     "We're upgrading TfL Rail stations to prepare for the Elizabeth line"
    ],
    "link": {
     "url": "/travel-information/improvements-and-projects/preparing-for-the-elizabeth-line",
     "image": {}
    },
    "image": {
     "url": "https://tfl.gov.uk/cdn/static/cms/images/promos/tfl-rail-train-teaser_rdax_400x200.jpg"
    },
    "wrapped": false
   },
   {
    "title": "Improving London's roads",
    "texts": [
     "See what we're doing to create safer, greener and more attractive streets"
    ],
    "link": {
     "url": "/campaign/our-plan-for-londons-roads",
     "image": {}
    },
    "image": {
     "url": "https://tfl.gov.uk/cdn/static/cms/images/promos/road-painting-teaser_rdax_400x200.jpg"
    },
    "wrapped": false
   }
  ]
 },
 "rhnav": {
  "cards": [
   {
    "template": "advert",
    "link": {
     "image": {}
    },
    "image": {},
    "wrapped": false
   }
  ]
 }
}