{
 "pageTitle": "Performance",
 "keywords": "TfL",
 "description": "The performance and value of the TfL Pension Fund.",
 "template": "page-content",
 "breadcrumbs": [
  {
   "style": "home",
   "title": "Home",
   "url": "/"
  },
  {
   "title": "TfL Pension Fund",
   "url": "/pensions/index"
  },
  {
   "title": "Fund management",
   "url": "/pensions/fund-management"
  },
  {
   "title": "Performance"
  }
 ],
 "title": {
  "title": "Performance",
  "card": {
   "link": {
    "image": {}
   },
   "image": {},
   "wrapped": false
  }
 },
 "body": {
  "primarys": [],
  "cards": [
   {
    "template": "content",
    "texts": [
     "{\"template\":\"intro\",\"texts\":[\"The performance and value of the TfL Pension Fund.\"],\"link\":{\"image\":{}},\"image\":{},\"wrapped\":false}",
     "{\"template\":\"htag\",\"level\":\"h3\",\"value\":\"Investment returns\"}",
     "The table below shows the total investment returns, net of fees, (including both capital and income) obtained on the Fund's assets (including property but excluding AVCs) for the one, three and five years to 31 March 2018 and the corresponding composite benchmark established by the Trustee as the prime performance comparator.  The benchmark quoted is a weighted average of indices relevant to the structure and is relevant throughout the time periods shown.",
     "{\"template\":\"table\",\"titles\":[\"\",\"\",\"\",\"\",\"\",\"Total Fund\",\"\",\"\",\"\",\"\",\"\",\"Annual return %\",\"Ex currency hedging\"],\"rows\":[[],[],[\"4.1\",\"3.6\",\"7.3\",\"8.4\",\"8.1\",\"8.8\"],[\"2.8\",\"3.2\",\"8.1\",\"8.7\",\"8.4\",\"8.7\"]]}",
     "This year's investment performance was 4.1%, 0.5% above the benchmark return of 3.6%. Over the three year period, returns were 7.3% per year, 1.1% below the benchmark. Over five years, returns were 8.1% per year, 0.7% below the benchmark.",
     "{\"template\":\"bulletlist\"}",
     "{\"template\":\"htag\",\"level\":\"h3\",\"value\":\"Value of the Fund\"}",
     "The value of the Fund over the last five years has been:",
     "{\"template\":\"table\",\"titles\":[\"\",\"\"],\"rows\":[[],[\"2018\",\"£10,337.8m\"],[\"2017\",\"£9,867.8m\"],[\"2016\",\"£8,211.4m\"],[\"2015\",\"£8,304.2m\"],[\"2014\",\"£7,311.9m\"]]}",
     "{\"template\":\"htag\",\"level\":\"h3\",\"value\":\"Assessing performance\"}",
     "The Fund participates in an independent investment performance measurement scheme organised by JP Morgan Investor Services which provides comparative information for assessing investment performance.  JP Morgan Investor Services calculates both the overall investment returns obtained on the Fund's assets and the returns obtained by the individual Investment Managers."
    ],
    "link": {
     "image": {}
    },
    "image": {},
    "wrapped": false
   }
  ]
 },
 "rhnav": {
  "cards": [
   {
    "template": "socialmediashare",
    "link": {
     "image": {}
    },
    "image": {},
    "wrapped": false
   },
   {
    "template": "listgroup",
    "style": "foldernav",
    "title": "TfL Pension Fund",
    "links": [
     {
      "title": "Your pension",
      "url": "/pensions/your-pension",
      "image": {}
     },
     {
      "title": "Fund management",
      "url": "/pensions/fund-management",
      "image": {}
     },
     {
      "title": "Trustee board",
      "url": "/pensions/fund-management/trustee-board",
      "image": {}
     },
     {
      "title": "Committees",
      "url": "/pensions/fund-management/committees",
      "image": {}
     },
     {
      "title": "Pension Consultative Council",
      "url": "/pensions/fund-management/pension-consultative-council",
      "image": {}
     },
     {
      "title": "Pensioners' Forum",
      "url": "/pensions/fund-management/pensioners-forum",
      "image": {}
     },
     {
      "title": "Pensions working group",
      "url": "/pensions/fund-management/pensions-working-group",
      "image": {}
     },
     {
      "title": "Annual members meeting",
      "url": "/pensions/fund-management/annual-meeting",
      "image": {}
     },
     {
      "title": "Investment management and principles",
      "url": "/pensions/fund-management/investment-management-and-principles",
      "image": {}
     },
     {
      "title": "Performance",
      "url": "/pensions/fund-management/performance",
      "image": {}
     },
     {
      "title": "Accounts",
      "url": "/pensions/fund-management/accounts",
      "image": {}
     },
     {
      "title": "Associations",
      "url": "/pensions/fund-management/associations",
      "image": {}
     },
     {
      "title": "Transport Benevolent Fund",
      "url": "/pensions/fund-management/transport-benevolent-fund",
      "image": {}
     },
     {
      "title": "Staff Welfare Fund",
      "url": "/pensions/fund-management/staff-welfare-fund",
      "image": {}
     },
     {
      "title": "Documents",
      "url": "/pensions/fund-management/documents",
      "image": {}
     },
     {
      "title": "Actuarial Valuation",
      "url": "/pensions/fund-management/actuarial-valuation",
      "image": {}
     },
     {
      "title": "Archive",
      "url": "/pensions/fund-management/archive",
      "image": {}
     },
     {
      "title": "Environmental, social and governance matters",
      "url": "/pensions/environmental-social-and-governance-matters",
      "image": {}
     },
     {
      "title": "News and publications",
      "url": "/pensions/news-and-publications",
      "image": {}
     },
     {
      "title": "Contact TfL Pension Fund",
      "url": "/pensions/contact",
      "image": {}
     }
    ],
    "link": {
     "title": "TfL Pension Fund",
     "url": "/pensions/contact",
     "image": {}
    },
    "image": {},
    "wrapped": false
   },
   {
    "template": "advert",
    "link": {
     "image": {}
    },
    "image": {},
    "wrapped": false
   }
  ]
 }
}