{
 "pageTitle": "Taxi meetings",
 "keywords": "TfL",
 "description": "Taxi meetings",
 "template": "page-content",
 "breadcrumbs": [
  {
   "style": "home",
   "title": "Home",
   "url": "/"
  },
  {
   "title": "Taxi \u0026 private hire",
   "url": "/info-for/taxis-and-private-hire/index"
  },
  {
   "title": "News and updates",
   "url": "/info-for/taxis-and-private-hire/driver-news-and-updates"
  },
  {
   "title": "Meetings",
   "url": "/info-for/taxis-and-private-hire/compliance-and-enforcement-meetings"
  },
  {
   "title": "Taxi meetings"
  }
 ],
 "title": {
  "title": "Taxi meetings",
  "card": {
   "link": {
    "image": {}
   },
   "image": {},
   "wrapped": false
  }
 },
 "body": {
  "primarys": [],
  "cards": [
   {
    "template": "content",
    "texts": [
     "{\"template\":\"intro\",\"texts\":[\"Information about our quarterly meetings with taxi trade representatives.\"],\"link\":{\"image\":{}},\"image\":{},\"wrapped\":false}",
     "{\"template\":\"listgroup\",\"style\":\"nocard\",\"links\":[{\"title\":\"Taxi engagement policy\",\"url\":\"/cdn/static/cms/documents/taxi-engagement-policy-april-2017.pdf\",\"icon\":\"download\",\"size\":\"PDF 100KB\",\"image\":{}}],\"link\":{\"image\":{}},\"image\":{},\"wrapped\":false}",
     "{\"template\":\"htag\",\"level\":\"h3\",\"value\":\"Taxi operational performance meetings\"}",
     "We hold quarterly meetings with taxi trade representatives on issues relating to licensing, compliance and enforcement. The actions of those meetings are available to read in the following documents:",
     "{\"template\":\"listgroup\",\"style\":\"nocard\",\"links\":[{\"title\":\"Notes and actions from taxi operational performance meeting February 2019\",\"url\":\"/cdn/static/cms/documents/taxi-operational-performance-seminar-summary-actions-february-2019.pdf\",\"icon\":\"download\",\"size\":\"PDF 206KB\",\"image\":{}},{\"title\":\"Taxi operational performance meeting February 2019 slides\",\"url\":\"/cdn/static/cms/documents/taxi-operational-performance-seminar-presentation-february-2019.pdf\",\"icon\":\"download\",\"size\":\"PDF 403KB\",\"image\":{}},{\"title\":\"Taxi operational performance meeting December 2018 slides\",\"url\":\"/cdn/static/cms/documents/taxi-operational-performance-meeting-december-2018-slides.pdf\",\"icon\":\"download\",\"size\":\"PDF 580KB\",\"image\":{}},{\"title\":\"Notes and actions from taxi operational performance meeting December 2018\",\"url\":\"/cdn/static/cms/documents/notes-actions-dec-2019.pdf\",\"icon\":\"download\",\"size\":\"PDF 106KB\",\"image\":{}},{\"title\":\"Notes and actions from taxi operational performance meeting August 2018\",\"url\":\"/cdn/static/cms/documents/taxi-operational-performance-meeting-notes-august-2018.pdf\",\"icon\":\"download\",\"size\":\"PDF 97KB\",\"image\":{}},{\"title\":\"Taxi operational performance meeting August 2018 slides\",\"url\":\"/cdn/static/cms/documents/taxi-operational-performance-seminar-presentation-august-2018.pdf\",\"icon\":\"download\",\"size\":\"PDF 591KB\",\"image\":{}},{\"title\":\"Notes and actions from taxi operational performance meeting May 2018\",\"url\":\"/cdn/static/cms/documents/taxi-operational-performance-meeting-notes-may-2018.pdf.pdf\",\"icon\":\"download\",\"size\":\"PDF.PDF 35KB\",\"image\":{}},{\"title\":\"Taxi operational performance meeting May 2018 slides\",\"url\":\"/cdn/static/cms/documents/taxi-operational-performance-seminar-presentation-may-2018.pdf\",\"icon\":\"download\",\"size\":\"PDF 793KB\",\"image\":{}},{\"title\":\"Notes and actions from taxi operational performance meeting February 2018\",\"url\":\"/cdn/static/cms/documents/taxi-operational-performance-meeting-notes-february-2018.pdf\",\"icon\":\"download\",\"size\":\"PDF 52KB\",\"image\":{}},{\"title\":\"Taxi operational performance meeting February 2018 slides\",\"url\":\"/cdn/static/cms/documents/taxi-operational-performance-meeting-february-2018-slides.pdf\",\"icon\":\"download\",\"size\":\"PDF 598KB\",\"image\":{}},{\"title\":\"Notes and actions from taxi operational performance meeting October 2017\",\"url\":\"/cdn/static/cms/documents/taxi-operational-performance-meeting-notes-october-2017.pdf\",\"icon\":\"download\",\"size\":\"PDF 146KB\",\"image\":{}},{\"title\":\"Taxi operational performance meeting October 2017 slides\",\"url\":\"/cdn/static/cms/documents/taxi-operational-performance-meeting-october-2017-slides.pdf\",\"icon\":\"download\",\"size\":\"PDF 763KB\",\"image\":{}},{\"title\":\"Notes and actions from taxi operational performance meeting July 2017\",\"url\":\"/cdn/static/cms/documents/taxi-operation-performance-seminar-notes-and-actions-20-july-2017.pdf\",\"icon\":\"download\",\"size\":\"PDF 97KB\",\"image\":{}},{\"title\":\"Taxi operational performance meeting July 2017 slides\",\"url\":\"/cdn/static/cms/documents/taxi-operational-performance-meeting-july-2017-slides.pdf\",\"icon\":\"download\",\"size\":\"PDF 682KB\",\"image\":{}},{\"title\":\"Notes and actions from taxi operational performance meeting April 2017\",\"url\":\"/cdn/static/cms/documents/notes-and-actions-from-taxi-operational-performance-meeting-april-2017.pdf\",\"icon\":\"download\",\"size\":\"PDF 90KB\",\"image\":{}},{\"title\":\"Taxi operational performance meeting April 2017 slides\",\"url\":\"/cdn/static/cms/documents/taxi-licensing-compliance-and-enforcement-april-2017-slides.pdf\",\"icon\":\"download\",\"size\":\"PDF 1.11MB\",\"image\":{}},{\"title\":\"Taxi licensing compliance and enforcement action tracker December 2016\",\"url\":\"/cdn/static/cms/documents/taxi-licensing-compliance-and-enforcement-december-2016-actions.pdf\",\"icon\":\"download\",\"size\":\"PDF 48KB\",\"image\":{}},{\"title\":\"Taxi licensing compliance and enforcement December 2016 slides\",\"url\":\"/cdn/static/cms/documents/taxi-licensing-compliance-and-enforcement-december-2016-slides.pdf\",\"icon\":\"download\",\"size\":\"PDF 1.14MB\",\"image\":{}},{\"title\":\"Taxi licensing compliance and enforcement action tracker October 2016\",\"url\":\"/cdn/static/cms/documents/taxi-licensing-compliance-and-enforcement-october-2016-actions.pdf\",\"icon\":\"download\",\"size\":\"PDF 46KB\",\"image\":{}},{\"title\":\"Taxi licensing compliance and enforcement October 2016 slides\",\"url\":\"/cdn/static/cms/documents/taxi-licensing-compliance-and-enforcement-october-2016-slides.pdf\",\"icon\":\"download\",\"size\":\"PDF 0.98MB\",\"image\":{}},{\"title\":\"Taxi licensing compliance and enforcement meeting action tracker August 2016\",\"url\":\"/cdn/static/cms/documents/taxi-licensing-compliance-and-enforcement-august-2016-actions.pdf\",\"icon\":\"download\",\"size\":\"PDF 48KB\",\"image\":{}},{\"title\":\"Taxi licensing compliance and enforcement August 2016 slides\",\"url\":\"/cdn/static/cms/documents/taxi-licensing-compliance-and-enforcement-august-2016-slides.pdf\",\"icon\":\"download\",\"size\":\"PDF 953KB\",\"image\":{}},{\"title\":\"Taxi licensing compliance and enforcement meeting action tracker June 2016\",\"url\":\"/cdn/static/cms/documents/taxi-licensing-compliance-and-enforcement-june-2016-actions.pdf\",\"icon\":\"download\",\"size\":\"PDF 54KB\",\"image\":{}},{\"title\":\"Taxi licensing compliance and enforcement June 2016 slides\",\"url\":\"/cdn/static/cms/documents/taxi-licensing-compliance-and-enforcement-june-2016-slides.pdf\",\"icon\":\"download\",\"size\":\"PDF 917KB\",\"image\":{}},{\"title\":\"Taxi licensing compliance and enforcement April 2016 slides\",\"url\":\"/cdn/static/cms/documents/taxi-licensing-compliance-and-enforcement-april-2016-slides.pdf\",\"icon\":\"download\",\"size\":\"PDF 838KB\",\"image\":{}},{\"title\":\"Taxi licensing compliance and enforcement meeting action tracker April 2016\",\"url\":\"/cdn/static/cms/documents/taxi-licensing-compliance-and-enforcement-april-2016-actions.pdf\",\"icon\":\"download\",\"size\":\"PDF 60KB\",\"image\":{}},{\"title\":\"Taxi licensing compliance and enforcement meeting action tracker January 2016\",\"url\":\"/cdn/static/cms/documents/taxi-licensing-compliance-and-enforcement-january-2016-actions.pdf\",\"icon\":\"download\",\"size\":\"PDF 134KB\",\"image\":{}},{\"title\":\"Taxi licensing compliance and enforcement meeting action tracker September 2015\",\"url\":\"/cdn/static/cms/documents/taxi-licensing-compliance-and-enforcement-meeting-september-2015-actions.pdf\",\"icon\":\"download\",\"size\":\"PDF 86KB\",\"image\":{}},{\"title\":\"Taxi licensing compliance and enforcement meeting action tracker July 2015\",\"url\":\"/cdn/static/cms/documents/taxi-licensing-compliance-and-enforcement-tracker-july-2015.pdf\",\"icon\":\"download\",\"size\":\"PDF 83KB\",\"image\":{}}],\"link\":{\"image\":{}},\"image\":{},\"wrapped\":false}"
    ],
    "link": {
     "image": {}
    },
    "image": {},
    "wrapped": false
   }
  ]
 },
 "rhnav": {
  "cards": [
   {
    "template": "socialmediashare",
    "link": {
     "image": {}
    },
    "image": {},
    "wrapped": false
   },
   {
    "template": "listgroup",
    "style": "foldernav",
    "title": "Taxi \u0026 private hire",
    "links": [
     {
      "title": "Licensing",
      "url": "/info-for/taxis-and-private-hire/licensing",
      "image": {}
     },
     {
      "title": "Compliance and enforcement",
      "url": "/info-for/taxis-and-private-hire/compliance-and-enforcement",
      "image": {}
     },
     {
      "title": "Ranks, regulation and policy",
      "url": "/info-for/taxis-and-private-hire/ranks-regulation-and-policy",
      "image": {}
     },
     {
      "title": "News and updates",
      "url": "/info-for/taxis-and-private-hire/driver-news-and-updates",
      "image": {}
     },
     {
      "title": "Taxi \u0026 private hire news",
      "url": "/info-for/taxis-and-private-hire/press-releases-and-news",
      "image": {}
     },
     {
      "title": "Meetings",
      "url": "/info-for/taxis-and-private-hire/compliance-and-enforcement-meetings",
      "image": {}
     },
     {
      "title": "Suburban Driver Forums",
      "url": "/info-for/taxis-and-private-hire/suburban-driver-forums",
      "image": {}
     },
     {
      "title": "Taxi meetings",
      "url": "/info-for/taxis-and-private-hire/taxi-meetings",
      "image": {}
     },
     {
      "title": "Private hire meetings",
      "url": "/info-for/taxis-and-private-hire/private-hire-meetings",
      "image": {}
     },
     {
      "title": "Notices \u0026 consultations",
      "url": "/info-for/taxis-and-private-hire/notices-and-consultations",
      "image": {}
     },
     {
      "title": "Contact Taxi \u0026 Private Hire",
      "url": "/info-for/taxis-and-private-hire/contact-taxis-and-private-hire",
      "image": {}
     },
     {
      "title": "Taxi and private hire comments",
      "url": "/info-for/taxis-and-private-hire/taxi-and-private-hire-comments",
      "image": {}
     },
     {
      "title": "Taxi delicensing",
      "url": "/info-for/taxis-and-private-hire/taxi-delicensing-scheme",
      "image": {}
     }
    ],
    "link": {
     "title": "Taxi \u0026 private hire",
     "url": "/info-for/taxis-and-private-hire/taxi-delicensing-scheme",
     "image": {}
    },
    "image": {},
    "wrapped": false
   },
   {
    "template": "advert",
    "link": {
     "image": {}
    },
    "image": {},
    "wrapped": false
   }
  ]
 }
}